LICENSE
MANIFEST.in
README
pavement.py
paver-minilib.zip
setup.cfg
setup.py
debian/changelog
src/auvyon/__init__.py
src/auvyon/config.py
src/auvyon.egg-info/PKG-INFO
src/auvyon.egg-info/SOURCES.txt
src/auvyon.egg-info/dependency_links.txt
src/auvyon.egg-info/requires.txt
src/auvyon.egg-info/top_level.txt
src/auvyon.egg-info/zip-safe
src/auvyon/audio/__init__.py
src/auvyon/audio/transcode.py
src/auvyon/imaging/__init__.py
src/auvyon/imaging/spectrograms.py
src/auvyon/imaging/waveforms.py
src/auvyon/metadata/__init__.py
src/auvyon/metadata/cue.py