Metadata-Version: 1.1
Name: auvyon
Version: 0.1
Summary: AuVyon - Audio-Visual Tools
Home-page: https://github.com/pyroscope/auvyon
Author: The PyroScope Project
Author-email: pyroscope.project@gmail.com
License: Copyright (c) 2011 The PyroScope Project <pyroscope.project@gmail.com>
Keywords: audio video metadata cli tool python
Platform: UNKNOWN
Classifier: Development Status :: 4 - Beta
Classifier: Environment :: Console
Classifier: Intended Audience :: End Users/Desktop
Classifier: Intended Audience :: Developers
Classifier: License :: OSI Approved :: GNU General Public License (GPL)
Classifier: Natural Language :: English
Classifier: Operating System :: OS Independent
Classifier: Programming Language :: Python :: 2.5
Classifier: Topic :: Multimedia
Classifier: Topic :: Multimedia :: Sound/Audio
Classifier: Topic :: Multimedia :: Video
Classifier: Topic :: Software Development :: Libraries :: Python Modules
Classifier: Topic :: Utilities
